odoo/addons/web_pivot_hide_total/README.rst
odoo/addons/web_pivot_hide_total/__init__.py
odoo/addons/web_pivot_hide_total/__manifest__.py
odoo/addons/web_pivot_hide_total/i18n/web_pivot_hide_total.pot
odoo/addons/web_pivot_hide_total/readme/CONFIGURATION.rst
odoo/addons/web_pivot_hide_total/readme/CONFIGURE.rst
odoo/addons/web_pivot_hide_total/readme/CONTRIBUTORS.rst
odoo/addons/web_pivot_hide_total/readme/DESCRIPTION.rst
odoo/addons/web_pivot_hide_total/readme/ROADMAP.rst
odoo/addons/web_pivot_hide_total/static/description/after.png
odoo/addons/web_pivot_hide_total/static/description/before.png
odoo/addons/web_pivot_hide_total/static/description/icon.png
odoo/addons/web_pivot_hide_total/static/description/index.html
odoo/addons/web_pivot_hide_total/static/src/js/views/pivot/pivot_model_hide_total.js
odoo/addons/web_pivot_hide_total/static/src/js/views/pivot/pivot_view_hide_total.js
odoo/addons/web_pivot_hide_total/views/web_pivot_hide_total_views.xml
odoo14_addon_web_pivot_hide_total-14.0.1.0.1.dist-info/METADATA
odoo14_addon_web_pivot_hide_total-14.0.1.0.1.dist-info/WHEEL
odoo14_addon_web_pivot_hide_total-14.0.1.0.1.dist-info/top_level.txt
odoo14_addon_web_pivot_hide_total-14.0.1.0.1.dist-info/RECORD
